{
  "todo": [
    {
      "id": "1",
      "title": "cars",
      "list": [
        {
          "item": "Lamborgini"
        },
        {
          "item": "Tesla"
        },
        {
          "item": "Audi"
        }
      ]
    },
    {
      "id": "2",
      "title": "colours",
      "list": [
        {
          "item": "Green"
        },
        {
          "item": "Yellow"
        },
        {
          "item": "Orange"
        }
      ]
    },
    {
      "id": "3",
      "title": "movies",
      "list": [
        {
          "item": "Ra-one"
        },
        {
          "item": "Krish"
        },
        {
          "item": "Superman"
        }
      ]
    },
    {
      "title": "dfsfd",
      "id": "_3Rq0t_"
    },
    {
      "title": "edfg",
      "id": "9-wDoZP"
    },
    {
      "title": "hgjhgjh",
      "id": "rgnxxAS"
    },
    {
      "title": "jghjhg",
      "id": "lxeIr9v"
    },
    {
      "title": "sdsd",
      "id": "sgtn6nf"
    },
    {
      "title": "sdfsd",
      "id": "ZB7bUEF"
    },
    {
      "title": "superan",
      "id": "6vXkXr0"
    },
    {
      "title": "superman",
      "id": "ZWEEDno"
    },
    {
      "title": "Thor",
      "id": "gXj5Okd"
    },
    {
      "title": "aaaa",
      "id": "paZqbFw"
    },
    {
      "title": "",
      "id": "5TCotiM"
    }
  ]
}